{"senders.":{"id":[77,337,176,96,239,2,22,725,333,8],"senders":["Mark McLoughlin","Dan Wendlandt","Jay Pipes","Thierry Carrez","Duncan McGreggor","Anne Gentle","Vishvananda Ishaya","Gary Kotton","Matt Joyce","Lorin Hochstein"],"sent":[77,77,72,71,70,56,56,48,48,45]},"senders.last year":{"id":[96,22,337,77,234,2,725,714,176,333],"senders":["Thierry Carrez","Vishvananda Ishaya","Dan Wendlandt","Mark McLoughlin","Joshua Harlow","Anne Gentle","Gary Kotton","David Kang","Jay Pipes","Matt Joyce"],"sent":[46,39,39,38,32,30,27,25,23,21]},"senders.last month":{}}