{"commits":10851,"first_date":"2013-04-04","last_date":"2013-08-03","committers":626,"authors":676,"files":10366,"branches":6,"repositories":45,"actions":31419,"added_lines":3190699,"removed_lines":1998691,"avg_commits_week":638.2941,"avg_files_week":609.7647,"avg_commits_author":16.0518,"avg_files_author":15.357,"companies":53,"companies_2006":0,"companies_2009":0,"companies_2012":61,"url":"https://github.com/openstack/api-site.git","type":"git","commits_7":831,"authors_7":177,"files_7":1487,"added_lines_7":125077,"removed_lines_7":67199,"commits_30":3447,"authors_30":391,"files_30":6085,"added_lines_30":1187779,"removed_lines_30":772307,"commits_90":8984,"authors_90":616,"files_90":9518,"added_lines_90":2819973,"removed_lines_90":1734161}