{"authors.":{"id":[1,39,33,81,46,284,77,24,55,2],"authors":["James E. Blair","Monty Taylor","Clark Boylan","Dirk Mueller","Julien Danjou","Steve Baker","Mark McLoughlin","Diane Fleming","Angus Salkeld","Anne Gentle"],"commits":[248,247,166,141,139,136,124,122,119,114]},"authors.last year":{"id":[1,39,33,81,46,284,77,24,55,2],"authors":["James E. Blair","Monty Taylor","Clark Boylan","Dirk Mueller","Julien Danjou","Steve Baker","Mark McLoughlin","Diane Fleming","Angus Salkeld","Anne Gentle"],"commits":[248,247,166,141,139,136,124,122,119,114]},"authors.last month":{"id":[1,348,39,284,77,46,851,33,55,281],"authors":["James E. Blair","Christian Berendt","Monty Taylor","Steve Baker","Mark McLoughlin","Julien Danjou","Andreas Jaeger","Clark Boylan","Angus Salkeld","Zane Bitter"],"commits":[66,58,48,42,40,32,31,30,30,29]}}