{"closers.":{"id":[22,100,222,12,368,725,176,406,90,211],"closers":["Vishvananda Ishaya","Dan Prince","Gabriel Hurley","Brian Waldon","Dolph Mathews","Gary Kotton","Jay Pipes","Salvatore Orlando","Rick Harris","Chris Behrens"],"closed":[331,323,318,272,169,166,142,134,131,128]},"closers.last year":{"id":[725,100,291,22,336,87,406,283,12,77],"closers":["Gary Kotton","Dan Prince","aaronorosen","Vishvananda Ishaya","Akihiro MOTOKI","john-griffith","Salvatore Orlando","Steven Hardy","Brian Waldon","Mark McLoughlin"],"closed":[139,114,102,99,90,86,85,80,76,74]},"closers.last month":{"id":[39,284,87,171,422,61,640,46,77,665],"closers":["Monty Taylor","Steve Baker","john-griffith","Armando Migliaccio","Yong Sheng Gong","Jeremy Stanley","Mark McClain","Julien Danjou","Mark McLoughlin","Phil Day"],"closed":[14,13,12,11,10,10,9,8,7,7]}}