{"first_date":"2010-11-11","last_date":"2013-07-07","sent":18851,"senders":1209,"repositories":1,"threads":10734,"url":"http://lists.openstack.org/pipermail/community/","sent_response":13269,"sent_init":5582,"sent_responses":13269,"sent_no_response":-5152,"thread_size_avg":1.2362,"thread_persons_avg":1.2212,"senders_init":883,"senders_response":905,"companies":48,"sent_7":453,"senders_7":154,"sent_14":835,"senders_14":227,"sent_30":1943,"senders_30":359,"sent_60":4057,"senders_60":512,"sent_90":6333,"senders_90":641,"sent_180":11011,"senders_180":816,"sent_365":17667,"senders_365":1056,"sent_730":18678,"senders_730":1176}