{"senders.":{"id":[96,77,39,93,47,176,118,2,22,372],"senders":["Thierry Carrez","Mark McLoughlin","Monty Taylor","Russell Bryant","Doug Hellmann","Jay Pipes","Sean Dague","Anne Gentle","Vishvananda Ishaya","Adam Young"],"sent":[524,485,312,306,285,280,249,236,206,200]},"senders.last year":{"id":[96,77,39,93,47,176,118,2,22,372],"senders":["Thierry Carrez","Mark McLoughlin","Monty Taylor","Russell Bryant","Doug Hellmann","Jay Pipes","Sean Dague","Anne Gentle","Vishvananda Ishaya","Adam Young"],"sent":[494,467,312,306,281,256,249,229,202,200]},"senders.last month":{"id":[96,77,258,93,262,118,39,47,368,176],"senders":["Thierry Carrez","Mark McLoughlin","Attila Fazekas","Russell Bryant","Robert Collins","Sean Dague","Monty Taylor","Doug Hellmann","Dolph Mathews","Jay Pipes"],"sent":[52,50,47,42,42,36,35,31,30,29]}}