{"first_date":"2010-11-11","last_date":"2013-07-22","sent":20200,"senders":1264,"repositories":1,"threads":11603,"url":"http://lists.openstack.org/pipermail/community/","sent_response":14336,"sent_init":5864,"sent_responses":14336,"sent_no_response":-5739,"thread_size_avg":1.2355,"thread_persons_avg":1.2211,"senders_init":921,"senders_response":956,"companies":53,"sent_7":649,"senders_7":188,"sent_14":1334,"senders_14":277,"sent_30":2195,"senders_30":375,"sent_60":4164,"senders_60":530,"sent_90":6986,"senders_90":667,"sent_180":11554,"senders_180":855,"sent_365":18856,"senders_365":1104,"sent_730":19984,"senders_730":1225}