{"authors.":{"id":[22,12,180,100,39,1,74,182,90,2],"authors":["Vishvananda Ishaya","Brian Waldon","Soren Hansen","Dan Prince","Monty Taylor","James E. Blair","SandyWalsh","Josh Kearney","Rick Harris","Anne Gentle"],"commits":[3290,1489,1254,1183,1095,1053,961,904,883,798]},"authors.last year":{"id":[1,77,39,33,283,2,100,281,93,12],"authors":["James E. Blair","Mark McLoughlin","Monty Taylor","Clark Boylan","Steven Hardy","Anne Gentle","Dan Prince","Zane Bitter","Russell Bryant","Brian Waldon"],"commits":[656,502,498,464,395,363,335,331,285,276]},"authors.last month":{"id":[39,1,33,55,281,77,24,2,368,90],"authors":["Monty Taylor","James E. Blair","Clark Boylan","Angus Salkeld","Zane Bitter","Mark McLoughlin","Diane Fleming","Anne Gentle","Dolph Mathews","Rick Harris"],"commits":[66,48,47,41,40,33,32,30,29,27]}}