{"authors.":{"id":[22,12,180,100,74,182,90,2,300,294],"authors":["Vishvananda Ishaya","Brian Waldon","Soren Hansen","Dan Prince","SandyWalsh","Josh Kearney","Rick Harris","Anne Gentle","andy","Todd Willey"],"commits":[3283,1485,1251,1128,961,904,882,764,763,741]},"authors.last year":{"id":[77,283,2,281,100,93,12,368,725,22],"authors":["Mark McLoughlin","Steven Hardy","Anne Gentle","Zane Bitter","Dan Prince","Russell Bryant","Brian Waldon","Dolph Mathews","Gary Kotton","Vishvananda Ishaya"],"commits":[491,395,329,321,305,301,276,257,251,243]},"authors.last month":{"id":[39,55,2,24,90,281,283,126,77,368],"authors":["Monty Taylor","Angus Salkeld","Anne Gentle","Diane Fleming","Rick Harris","Zane Bitter","Steven Hardy","Michael Still","Mark McLoughlin","Dolph Mathews"],"commits":[67,45,41,37,31,30,29,27,26,25]}}