{"commits":65365,"first_date":"2010-05-27","last_date":"2013-06-07","authors":1024,"committers":970,"files":32954,"branches":7,"repositories":50,"actions":159763,"added_lines":8518852,"removed_lines":5547282,"avg_commits_week":413.7025,"avg_files_week":208.5696,"avg_commits_author":63.833,"avg_files_author":34.1492,"companies":59,"companies_2006":0,"companies_2009":0,"companies_2012":55,"url":"https://github.com/openstack/api-site.git","type":"git","commits_7":470,"authors_7":100,"files_7":955,"added_lines_7":69407,"removed_lines_7":51990,"commits_30":2599,"authors_30":330,"files_30":3935,"added_lines_30":893727,"removed_lines_30":432244,"commits_90":6940,"authors_90":503,"files_90":7239,"added_lines_90":1553238,"removed_lines_90":821236,"commits_365":25864,"authors_365":813,"files_365":16168,"added_lines_365":3483832,"removed_lines_365":2139730}