{"commits":65684,"first_date":"2010-05-27","last_date":"2013-06-11","authors":1036,"committers":979,"files":33033,"branches":7,"repositories":50,"actions":160601,"added_lines":8626342,"removed_lines":5619935,"avg_commits_week":415.7215,"avg_files_week":209.0696,"avg_commits_author":63.4015,"avg_files_author":33.9148,"companies":59,"companies_2006":0,"companies_2009":0,"companies_2012":55,"url":"https://github.com/openstack/api-site.git","type":"git","commits_7":528,"authors_7":123,"files_7":894,"added_lines_7":125812,"removed_lines_7":90059,"commits_30":2659,"authors_30":342,"files_30":3850,"added_lines_30":978645,"removed_lines_30":487424,"commits_90":6811,"authors_90":508,"files_90":7102,"added_lines_90":1608819,"removed_lines_90":871540,"commits_365":26020,"authors_365":825,"files_365":16185,"added_lines_365":3573666,"removed_lines_365":2202508}